{
  "timestamp": "2026-04-07T13:25:53.307866+00:00",
  "links": [
    {
      "url": "https://t.me/luluexch",
      "source_channel_id": -2292758419,
      "source_channel_name": "BigCric",
      "message_text": "**__\u26a0\ufe0f\u00a0FRAUD GAMING PLATFORM SE BACHO\u00a0\u26a0\ufe0f\n\nPLAY ONLY WITH,\ud83d\udd31LULU EXCHANGE\ud83d\udd31\n\n\ud83c\udf10 Top Class Websites \ud83d\udc47\n\u25cf __****__Luluexch.co__****__ (Sign Up Now)\n\u25cf __****__My99exch.black__****__\n\u25cf __****__Mytiger247.pro__****__\n\u25cf __****__Allpanelexch9.co__****__\n\u2795 Aur 5 Premium Sites \u2013 WhatsApp par Available__.\n\n6\u20e3 Khud Ki Sites Hai Inki,Baaki Sab Aapko Sasti Sites Par Khelne Bolte Hai Lekin LULU EXCH Only Premium Sites Deta Hai...\n\nTELEGRAM LINK \ud83d\udc47\n****https://t.me/luluexch****\n\nOPEN GROUP \ud83d\udd17 \ud83d\udc47 \n****https://t.me/luluexchog****\n\n5% Bonus On Every Refill And New \ud83c\udd94 On Any Amount Whatsapp Now\ud83d\udc47\n****http://wa.link/luluexch01****\n****http://wa.link/luluexch01**",
      "posted_time": "2026-04-07T11:15:37+00:00"
    },
    {
      "url": "https://t.me/luluexchog",
      "source_channel_id": -2292758419,
      "source_channel_name": "BigCric",
      "message_text": "**__\u26a0\ufe0f\u00a0FRAUD GAMING PLATFORM SE BACHO\u00a0\u26a0\ufe0f\n\nPLAY ONLY WITH,\ud83d\udd31LULU EXCHANGE\ud83d\udd31\n\n\ud83c\udf10 Top Class Websites \ud83d\udc47\n\u25cf __****__Luluexch.co__****__ (Sign Up Now)\n\u25cf __****__My99exch.black__****__\n\u25cf __****__Mytiger247.pro__****__\n\u25cf __****__Allpanelexch9.co__****__\n\u2795 Aur 5 Premium Sites \u2013 WhatsApp par Available__.\n\n6\u20e3 Khud Ki Sites Hai Inki,Baaki Sab Aapko Sasti Sites Par Khelne Bolte Hai Lekin LULU EXCH Only Premium Sites Deta Hai...\n\nTELEGRAM LINK \ud83d\udc47\n****https://t.me/luluexch****\n\nOPEN GROUP \ud83d\udd17 \ud83d\udc47 \n****https://t.me/luluexchog****\n\n5% Bonus On Every Refill And New \ud83c\udd94 On Any Amount Whatsapp Now\ud83d\udc47\n****http://wa.link/luluexch01****\n****http://wa.link/luluexch01**",
      "posted_time": "2026-04-07T11:15:37+00:00"
    },
    {
      "url": "http://wa.link/luluexch01",
      "source_channel_id": -2292758419,
      "source_channel_name": "BigCric",
      "message_text": "**__\u26a0\ufe0f\u00a0FRAUD GAMING PLATFORM SE BACHO\u00a0\u26a0\ufe0f\n\nPLAY ONLY WITH,\ud83d\udd31LULU EXCHANGE\ud83d\udd31\n\n\ud83c\udf10 Top Class Websites \ud83d\udc47\n\u25cf __****__Luluexch.co__****__ (Sign Up Now)\n\u25cf __****__My99exch.black__****__\n\u25cf __****__Mytiger247.pro__****__\n\u25cf __****__Allpanelexch9.co__****__\n\u2795 Aur 5 Premium Sites \u2013 WhatsApp par Available__.\n\n6\u20e3 Khud Ki Sites Hai Inki,Baaki Sab Aapko Sasti Sites Par Khelne Bolte Hai Lekin LULU EXCH Only Premium Sites Deta Hai...\n\nTELEGRAM LINK \ud83d\udc47\n****https://t.me/luluexch****\n\nOPEN GROUP \ud83d\udd17 \ud83d\udc47 \n****https://t.me/luluexchog****\n\n5% Bonus On Every Refill And New \ud83c\udd94 On Any Amount Whatsapp Now\ud83d\udc47\n****http://wa.link/luluexch01****\n****http://wa.link/luluexch01**",
      "posted_time": "2026-04-07T11:15:37+00:00"
    },
    {
      "url": "https://t.me/luluexch",
      "source_channel_id": -2946703793,
      "source_channel_name": "CRICSTERSS ANALYSTS",
      "message_text": "**__\u26a0\ufe0f\u00a0FRAUD GAMING PLATFORM SE BACHO\u00a0\u26a0\ufe0f\n\nPLAY ONLY WITH,\ud83d\udd31LULU EXCHANGE\ud83d\udd31\n\n\ud83c\udf10 Top Class Websites \ud83d\udc47\n\u25cf __****__Luluexch.co__****__ (Sign Up Now)\n\u25cf __****__My99exch.black__****__\n\u25cf __****__Mytiger247.pro__****__\n\u25cf __****__Allpanelexch9.co__****__\n\u2795 Aur 5 Premium Sites \u2013 WhatsApp par Available__.\n\n6\u20e3 Khud Ki Sites Hai Inki,Baaki Sab Aapko Sasti Sites Par Khelne Bolte Hai Lekin LULU EXCH Only Premium Sites Deta Hai...\n\nTELEGRAM LINK \ud83d\udc47\n****https://t.me/luluexch****\n\nOPEN GROUP \ud83d\udd17 \ud83d\udc47 \n****https://t.me/luluexchog****\n\n5% Bonus On Every Refill And New \ud83c\udd94 On Any Amount Whatsapp Now\ud83d\udc47\n****http://wa.link/luluexch01****\n****http://wa.link/luluexch01**",
      "posted_time": "2026-04-07T11:15:37+00:00"
    },
    {
      "url": "https://t.me/luluexchog",
      "source_channel_id": -2946703793,
      "source_channel_name": "CRICSTERSS ANALYSTS",
      "message_text": "**__\u26a0\ufe0f\u00a0FRAUD GAMING PLATFORM SE BACHO\u00a0\u26a0\ufe0f\n\nPLAY ONLY WITH,\ud83d\udd31LULU EXCHANGE\ud83d\udd31\n\n\ud83c\udf10 Top Class Websites \ud83d\udc47\n\u25cf __****__Luluexch.co__****__ (Sign Up Now)\n\u25cf __****__My99exch.black__****__\n\u25cf __****__Mytiger247.pro__****__\n\u25cf __****__Allpanelexch9.co__****__\n\u2795 Aur 5 Premium Sites \u2013 WhatsApp par Available__.\n\n6\u20e3 Khud Ki Sites Hai Inki,Baaki Sab Aapko Sasti Sites Par Khelne Bolte Hai Lekin LULU EXCH Only Premium Sites Deta Hai...\n\nTELEGRAM LINK \ud83d\udc47\n****https://t.me/luluexch****\n\nOPEN GROUP \ud83d\udd17 \ud83d\udc47 \n****https://t.me/luluexchog****\n\n5% Bonus On Every Refill And New \ud83c\udd94 On Any Amount Whatsapp Now\ud83d\udc47\n****http://wa.link/luluexch01****\n****http://wa.link/luluexch01**",
      "posted_time": "2026-04-07T11:15:37+00:00"
    },
    {
      "url": "http://wa.link/luluexch01",
      "source_channel_id": -2946703793,
      "source_channel_name": "CRICSTERSS ANALYSTS",
      "message_text": "**__\u26a0\ufe0f\u00a0FRAUD GAMING PLATFORM SE BACHO\u00a0\u26a0\ufe0f\n\nPLAY ONLY WITH,\ud83d\udd31LULU EXCHANGE\ud83d\udd31\n\n\ud83c\udf10 Top Class Websites \ud83d\udc47\n\u25cf __****__Luluexch.co__****__ (Sign Up Now)\n\u25cf __****__My99exch.black__****__\n\u25cf __****__Mytiger247.pro__****__\n\u25cf __****__Allpanelexch9.co__****__\n\u2795 Aur 5 Premium Sites \u2013 WhatsApp par Available__.\n\n6\u20e3 Khud Ki Sites Hai Inki,Baaki Sab Aapko Sasti Sites Par Khelne Bolte Hai Lekin LULU EXCH Only Premium Sites Deta Hai...\n\nTELEGRAM LINK \ud83d\udc47\n****https://t.me/luluexch****\n\nOPEN GROUP \ud83d\udd17 \ud83d\udc47 \n****https://t.me/luluexchog****\n\n5% Bonus On Every Refill And New \ud83c\udd94 On Any Amount Whatsapp Now\ud83d\udc47\n****http://wa.link/luluexch01****\n****http://wa.link/luluexch01**",
      "posted_time": "2026-04-07T11:15:37+00:00"
    },
    {
      "url": "https://khel-box.github.io/Willext/",
      "source_channel_id": -2100926631,
      "source_channel_name": "Cricket News",
      "message_text": "**IPL\n\nWillo\n****https://khel-box.github.io/Willext/**",
      "posted_time": "2026-04-06T14:31:42+00:00"
    }
  ]
}